Metadata-Version: 1.2
Name: othoz-adding-sum
Version: 0.1.1
Summary: Othoz ML take home test
Home-page: https://github.com/narendhrancs/othoz_adding_sum
Author: narendhrancs@gmail.com
License: UNKNOWN
Platform: UNKNOWN
Requires-Python: >=3.6
